skoloCliParser.py
skolo/__init__.py
skolo/caseObjects.py
skolo-0.1.4.dist-info/LICENSE
skolo-0.1.4.dist-info/METADATA
skolo-0.1.4.dist-info/WHEEL
skolo-0.1.4.dist-info/entry_points.txt
skolo-0.1.4.dist-info/top_level.txt
skolo-0.1.4.dist-info/RECORD
