Metadata-Version: 2.1
Name: skolo
Version: 0.1.4
Summary: A command line tool and python package for SkoloCFD
Home-page: https://skolocfd.com/docs?topic=Api
Author: Skolo, LLC
Author-email: support@skolocfd.com
License: MIT License
Classifier: Programming Language :: Python :: 3.11
Classifier: License :: OSI Approved :: GNU General Public License v3 (GPLv3)
Requires-Python: >=3.0
License-File: LICENSE
Requires-Dist: requests>=2.20
Requires-Dist: python-dateutil>=2
